{"config":{"version":"0.1.0","sharedDir":"shared","dependenciesDir":"extern","info":{"name":"Conditional Dependencies","id":"conditional-dependencies","version":"0.3.0","url":"https://github.com/RedBrumbler/ConditionalDependencies","additionalData":{"headersOnly":true,"cmake":false,"branchName":"version/v0_3_0"}},"workspace":{"scripts":{"build":["pwsh ./build.ps1"]}},"dependencies":[{"id":"scotland2","versionRange":"*","additionalData":{}}]},"restoredDependencies":[{"dependency":{"id":"scotland2","versionRange":"=0.1.4","additionalData":{"soLink":"https://github.com/sc2ad/scotland2/releases/download/v0.1.4/libsl2.so","debugSoLink":"https://github.com/sc2ad/scotland2/releases/download/v0.1.4/debug_libsl2.so","overrideSoName":"libsl2.so","branchName":"version/v0_1_4"}},"version":"0.1.4"}]}